petit_mail/__init__.py
petit_mail/data_struct.py
petit_mail/render_functions.py
petit_mail/server.py
petit_mail/utils.py
petit_mail/senders/SMTP_implem.py
petit_mail/senders/__init__.py
petit_mail/senders/gmail_implem.py
petit_mail/senders/interface.py
petit_mail/template_db/__init__.py
petit_mail/template_db/interface.py
petit_mail/template_db/local_implem.py
petit_mail/template_db/minio_implem.py
petit_mail/template_db/utils.py
petit_mail-0.1.5.dist-info/LICENSE.txt
petit_mail-0.1.5.dist-info/METADATA
petit_mail-0.1.5.dist-info/WHEEL
petit_mail-0.1.5.dist-info/top_level.txt
petit_mail-0.1.5.dist-info/RECORD
