Metadata-Version: 2.1
Name: petit-mail
Version: 0.1.5
Summary: An easy way to send templated emails using an HTTP interface
Home-page: https://github.com/Plawn/petit_mail
Author: Plawn
Author-email: plawn.yay@gmail.com
License: apache-2.0
Platform: UNKNOWN
Requires-Python: >=3.8
Requires-Dist: fastapi
Requires-Dist: uvicorn
Requires-Dist: Jinja2
Requires-Dist: premailer
Requires-Dist: minio
Requires-Dist: pyyaml
Requires-Dist: google-api-python-client
Requires-Dist: google-auth-httplib2
Requires-Dist: google-auth-oauthlib
Requires-Dist: oauth2client
